clidat/__init__.py
clidat/auth.py
clidat/commands/__init__.py
clidat/commands/accounting.py
clidat/commands/platform.py
clidat/main.py
clidat/meta.py
clidat/tui/viewer.py
clidat-0.1.2.dist-info/LICENSE.md
clidat-0.1.2.dist-info/METADATA
clidat-0.1.2.dist-info/WHEEL
clidat-0.1.2.dist-info/entry_points.txt
clidat-0.1.2.dist-info/RECORD
