Metadata-Version: 2.1
Name: clidat
Version: 0.1.2
Summary: CLI Tool for inspecting JSON Data from the Codat API
License: MIT
Author: Peter Simpson
Requires-Python: >=3.10,<4.0
Classifier: License :: OSI Approved :: MIT License
Classifier: Programming Language :: Python :: 3
Classifier: Programming Language :: Python :: 3.10
Classifier: Programming Language :: Python :: 3.11
Requires-Dist: click (>=8.1.3,<9.0.0)
Requires-Dist: pycompanydata (>=0.1.2,<0.2.0)
Requires-Dist: textual (>=0.18.0,<0.19.0)
